ga_opt.py
gahpo-0.1.4.dist-info/METADATA
gahpo-0.1.4.dist-info/WHEEL
gahpo-0.1.4.dist-info/top_level.txt
gahpo-0.1.4.dist-info/RECORD
