Metadata-Version: 2.1
Name: gahpo
Version: 0.1.4
Summary: A Genetic Algorithm with Stochastic Multi-mutations for HPO 
Home-page: https://github.com/ki4420/ga-hpo
Author: ChulKim
Author-email: scotty@thingspire.com
License: UNKNOWN
Download-URL: https://github.com/ki4420/ga-hpo/archive/0.0.tar.gz
Keywords: ga-hpo
Platform: UNKNOWN
Classifier: Programming Language :: Python :: 3
Classifier: Programming Language :: Python :: 3.2
Classifier: Programming Language :: Python :: 3.3
Classifier: Programming Language :: Python :: 3.4
Classifier: Programming Language :: Python :: 3.5
Classifier: Programming Language :: Python :: 3.6
Classifier: Programming Language :: Python :: 3.7
Requires-Python: >=3
